[
  {
    "id": 1,
    "name": "Господин",
    "surname": "Лайонел",
    "skills": ["react", "angular", "keyframe"]
  }, {
    "id": 2,
    "name": "Господин",
    "surname": "Горацио",
    "skills": ["angular", "angular4"]
  }, {
    "id": 3,
    "name": "Господин",
    "surname": "Вацлав",
    "skills": ["vue", "vanilla", "keyframe"]
  }, {
    "id": 4,
    "name": "Господин",
    "surname": "Этельвольф",
    "skills": ["react", "angular", "vue"]
  },{
    "id": 5,
    "name": "Господин",
    "surname": "Леопольд",
    "skills": ["react", "angular4", "keyframe"]
  }, {
    "id": 6,
    "name": "Господин",
    "surname": "Вольдемар",
    "skills": ["react", "angular", "vue", "keyframe"]
  }, {
    "id": 7,
    "name": "Господин",
    "surname": "Рудольф",
    "skills": ["angular", "vue", "vanilla", "angular4"]
  }
]